seaborn_polars.py
seaborn_polars-0.0.2.6.dist-info/LICENSE
seaborn_polars-0.0.2.6.dist-info/METADATA
seaborn_polars-0.0.2.6.dist-info/WHEEL
seaborn_polars-0.0.2.6.dist-info/top_level.txt
seaborn_polars-0.0.2.6.dist-info/RECORD
