Metadata-Version: 2.1
Name: seaborn-polars
Version: 0.0.2.6
Summary: Wrapper for plotting with seaborn using Polars dataframes and lazyframes
Author: Pavel Cherepanskiy
Classifier: Programming Language :: Python :: 3
Classifier: License :: OSI Approved :: Apache Software License
Classifier: Operating System :: OS Independent
Requires-Python: >=3.8
License-File: LICENSE
